test_archiver/ArchiverRobotListener.py
test_archiver/__init__.py
test_archiver/archiver.py
test_archiver/archiver_listeners.py
test_archiver/configs.py
test_archiver/database.py
test_archiver/output_parser.py
test_archiver/version.py
test_archiver/schemas/README.md
test_archiver/schemas/schema_postgres.sql
test_archiver/schemas/schema_sqlite.sql
test_archiver/schemas/migrations/postgres/0001-schema_update_table_and_log_message_index.sql
test_archiver/schemas/migrations/postgres/0002-execution_paths.sql
test_archiver/schemas/migrations/sqlite/0001-schema_update_table_and_log_message_index.sql
test_archiver/schemas/migrations/sqlite/0002-execution_paths.sql
test_archiver/schemas/migrations/sqlite/testing/10001-minor_test_update1.sql
test_archiver/schemas/migrations/sqlite/testing/10002-minor_test_update2.sql
test_archiver/schemas/migrations/sqlite/testing/10003-major_test_update.sql
testarchiver2-1.0.1.data/scripts/diff2change_context_list.py
testarchiver2-1.0.1.dist-info/LICENSE
testarchiver2-1.0.1.dist-info/METADATA
testarchiver2-1.0.1.dist-info/WHEEL
testarchiver2-1.0.1.dist-info/entry_points.txt
testarchiver2-1.0.1.dist-info/top_level.txt
testarchiver2-1.0.1.dist-info/RECORD
