Metadata-Version: 2.1
Name: testarchiver2
Version: 1.0.1
Summary: Tools for serialising test results to SQL database
Home-page: https://github.com/aaltat/TestArchiver
Author: Tatu Aalto
Author-email: aalto.tatu@gmail.com
License: Apache License 2.0
Keywords: robotframework test report history
Platform: UNKNOWN
Classifier: Programming Language :: Python :: 3
Classifier: Operating System :: OS Independent
Classifier: Topic :: Software Development :: Testing
Requires-Python: >=3.5
Requires-Dist: psycopg2-binary (>=2.8.5)
